aiodata/__init__.py
aiodata/client.py
aiodata/schema.psql
aiodata/server.py
aiodata-3.0.0.dist-info/LICENCE
aiodata-3.0.0.dist-info/METADATA
aiodata-3.0.0.dist-info/WHEEL
aiodata-3.0.0.dist-info/entry_points.txt
aiodata-3.0.0.dist-info/top_level.txt
aiodata-3.0.0.dist-info/RECORD
